server.py
iflow_mcp_gomarble_ai_google_analytics_mcp_server-1.0.0.dist-info/licenses/LICENSE
oauth/__init__.py
oauth/google_auth.py
iflow_mcp_gomarble_ai_google_analytics_mcp_server-1.0.0.dist-info/METADATA
iflow_mcp_gomarble_ai_google_analytics_mcp_server-1.0.0.dist-info/WHEEL
iflow_mcp_gomarble_ai_google_analytics_mcp_server-1.0.0.dist-info/entry_points.txt
iflow_mcp_gomarble_ai_google_analytics_mcp_server-1.0.0.dist-info/top_level.txt
iflow_mcp_gomarble_ai_google_analytics_mcp_server-1.0.0.dist-info/RECORD
