Metadata-Version: 2.4
Name: iflow-mcp_gomarble-ai_google-analytics-mcp-server
Version: 1.0.0
Summary: Google Analytics 4 MCP Server - FastMCP-powered Model Context Protocol server for Google Analytics 4 API integration
Requires-Python: >=3.10
License-File: LICENSE
Requires-Dist: fastmcp>=0.8.0
Requires-Dist: requests>=2.31.0
Requires-Dist: python-dotenv>=1.0.0
Requires-Dist: google-auth>=2.23.0
Requires-Dist: google-auth-oauthlib>=1.1.0
Requires-Dist: google-auth-httplib2>=0.1.1
Requires-Dist: urllib3>=2.0.0
Requires-Dist: typing-extensions>=4.0.0
Dynamic: license-file
Dynamic: requires-python
